segm/_segm.cpython-39-x86_64-linux-gnu.so
segm/__init__.py
segm.libs/libwebp-63152597.so.6.0.2
segm.libs/libflann-bf7be2e9.so.1.9.1
segm.libs/libflann_cpp-91f46df7.so.1.9.1
segm.libs/liblz4-b5d80b8d.so.1.7.1
segm.libs/libpng16-121b9de7.so.16.28.0
segm.libs/libjbig-b30cd8bd.so.0
segm.libs/libgif-a68219f4.so.7.0.0
segm.libs/libtiff-e2a5092b.so.5.2.6
segm.libs/libopenjp2-a0c5d12e.so.2.1.2
segm.libs/liblzma-9c0610aa.so.5.2.2
segm.libs/libjpeg-8afa139c.so.62.2.0
segm.libs/liblept-57487a5d.so.5.0.1
segm.libs/libgomp-ce6cf6a9.so.1.0.0
segm-0.1.3.dist-info/top_level.txt
segm-0.1.3.dist-info/WHEEL
segm-0.1.3.dist-info/METADATA
segm-0.1.3.dist-info/RECORD
