Metadata-Version: 2.1
Name: segm
Version: 0.1.3
Summary: A set of functions for page image segementation.
Author: Sergey Mikhno
Author-email: sergey.mikhno@gmail.com
